colour/__init__.py
colour/py.typed
colour/adaptation/__init__.py
colour/adaptation/cie1994.py
colour/adaptation/cmccat2000.py
colour/adaptation/fairchild1990.py
colour/adaptation/fairchild2020.py
colour/adaptation/vonkries.py
colour/adaptation/zhai2018.py
colour/adaptation/datasets/__init__.py
colour/adaptation/datasets/cat.py
colour/adaptation/tests/__init__.py
colour/adaptation/tests/test__init__.py
colour/adaptation/tests/test_cie1994.py
colour/adaptation/tests/test_cmccat2000.py
colour/adaptation/tests/test_fairchild1990.py
colour/adaptation/tests/test_fairchild2020.py
colour/adaptation/tests/test_vonkries.py
colour/adaptation/tests/test_zhai2018.py
colour/algebra/__init__.py
colour/algebra/common.py
colour/algebra/extrapolation.py
colour/algebra/interpolation.py
colour/algebra/prng.py
colour/algebra/regression.py
colour/algebra/coordinates/__init__.py
colour/algebra/coordinates/transformations.py
colour/algebra/coordinates/tests/__init__.py
colour/algebra/coordinates/tests/test_transformations.py
colour/algebra/tests/__init__.py
colour/algebra/tests/test_common.py
colour/algebra/tests/test_extrapolation.py
colour/algebra/tests/test_interpolation.py
colour/algebra/tests/test_prng.py
colour/algebra/tests/test_regression.py
colour/appearance/__init__.py
colour/appearance/atd95.py
colour/appearance/cam16.py
colour/appearance/ciecam02.py
colour/appearance/ciecam16.py
colour/appearance/hellwig2022.py
colour/appearance/hke.py
colour/appearance/hunt.py
colour/appearance/kim2009.py
colour/appearance/llab.py
colour/appearance/nayatani95.py
colour/appearance/rlab.py
colour/appearance/zcam.py
colour/appearance/tests/__init__.py
colour/appearance/tests/test_atd95.py
colour/appearance/tests/test_cam16.py
colour/appearance/tests/test_ciecam02.py
colour/appearance/tests/test_ciecam16.py
colour/appearance/tests/test_hellwig2022.py
colour/appearance/tests/test_hke.py
colour/appearance/tests/test_hunt.py
colour/appearance/tests/test_kim2009.py
colour_science-0.4.5.dist-info/METADATA
colour_science-0.4.5.dist-info/WHEEL
colour_science-0.4.5.dist-info/licenses/LICENSE
colour_science-0.4.5.dist-info/RECORD
