Metadata-Version: 2.3
Name: colour-science
Version: 0.4.5
Summary: Colour Science for Python
Project-URL: Homepage, https://www.colour-science.org
Project-URL: Documentation, https://readthedocs.org
Project-URL: Repository, https://github.com/colour-science/colour
Project-URL: Issues, https://github.com/colour-science/colour/issues
Project-URL: Changelog, https://github.com/colour-science/colour/releases
Author-email: Colour Developers <colour-developers@colour-science.org>
Maintainer-email: Colour Developers <colour-developers@colour-science.org>
License: BSD-3-Clause
License-File: LICENSE
Keywords: color,color-science,color-space,color-spaces,colorspace,colorspaces,colour,colour-science,colour-space,colour-spaces,colourspace,colourspaces,data,dataset,datasets,python,spectral-data,spectral-dataset,spectral-datasets
Classifier: Development Status :: 3 - Alpha
Classifier: Environment :: Console
Classifier: Intended Audience :: Developers
Classifier: Intended Audience :: Science/Research
Classifier: License :: OSI Approved
Classifier: Natural Language :: English
Classifier: Operating System :: OS Independent
Classifier: Programming Language :: Python :: 3
Classifier: Topic :: Scientific/Engineering
Classifier: Topic :: Software Development
Requires-Python: <3.14,>=3.10
Requires-Dist: imageio<3,>=2
Requires-Dist: numpy<3,>=1.24
Requires-Dist: scipy<2,>=1.10
Requires-Dist: trimesh>=4
Requires-Dist: typing-extensions<5,>=4
Provides-Extra: docs
Requires-Dist: biblib-simple; extra == 'docs'
Requires-Dist: pydata-sphinx-theme; extra == 'docs'
Requires-Dist: restructuredtext-lint; extra == 'docs'
Requires-Dist: sphinx; extra == 'docs'
Requires-Dist: sphinxcontrib-bibtex; extra == 'docs'
Provides-Extra: meshing
Requires-Dist: trimesh<5,>=4; extra == 'meshing'
Provides-Extra: optional
Requires-Dist: matplotlib>=3.7; extra == 'optional'
Requires-Dist: networkx<4,>=3; extra == 'optional'
Requires-Dist: opencolorio<3,>=2; extra == 'optional'
Requires-Dist: pandas<3,>=2; extra == 'optional'
Requires-Dist: pydot<4,>=3; extra == 'optional'
Requires-Dist: tqdm<5,>=4; extra == 'optional'
Requires-Dist: xxhash<4,>=3; extra == 'optional'
